apb_design_spec/code/apb_slave.v
module apb_slave #(
    parameter DATA_WD = 8,
    parameter ADDR_WD = 8 
) (
    input                    clk,
    input                    rst_n,
    input                    psel,
    input                    penable,
    input                    pwrite,
    input  [ADDR_WD - 1 : 0] paddr,
    input  [DATA_WD - 1 : 0] pwdata,
    output [DATA_WD - 1 : 0] prdata,
    output                   pready
);

localparam ADDR_MAX = (1 << ADDR_WD);

reg [DATA_WD - 1 : 0] mem [ADDR_MAX - 1 : 0];

localparam [1:0] IDLE = 2'b00;
localparam [1:0] SETUP = 2'b01;
localparam [1:0] ACCESS = 2'b11; 

reg [1:0] state,next_state;

// assign pready = 1'b1;
//control path
wire apb_fire;
assign apb_fire = psel && penable && pready;


always @(posedge clk or negedge rst_n) begin
    if(!rst_n) begin
        state <= IDLE;
    end
    else begin
        state <= next_state;
    end
end

always @(*) begin
    case(state) 
        IDLE: begin
            if(psel) begin
                next_state = SETUP;
            end
            else begin
                next_state = IDLE;
            end
        end
        SETUP: begin
            next_state = ACCESS;
        end
        ACCESS: begin
            if(!pready) begin
                next_state = ACCESS;
            end
            else if(psel) begin
                next_state = SETUP;
            end
            else begin
                next_state = IDLE;
            end
        end
        default: begin
            next_state = IDLE;
        end
    endcase
end

reg r_pready;
assign pready = r_pready;
always @(*) begin
    case(state)
        IDLE: begin
            r_pready = 1'b0;            
        end 
        SETUP: begin
            r_pready = 1'b0;            
        end
        ACCESS: begin
            if(psel && penable) begin
                r_pready = 1'b1;
            end
            else begin
                r_pready = 1'b0;
            end
        end
        default: begin
        end
    endcase
end

//data path

always @(posedge clk or negedge rst_n) begin
    if(!rst_n) begin
    end
    else if(apb_fire) begin
        mem[paddr] <= pwdata;
    end
end

assign prdata = mem[paddr];

endmodule

apb_design_spec/code/apb_master.v
module apb_master #(
    parameter DATA_WD = 8,
    parameter ADDR_WD = 8
) (
    input                         clk,
    input                         rst_n,
    input [DATA_WD + ADDR_WD : 0] cmd_in,
    input                         cmd_vld,
    input [DATA_WD - 1 : 0]       prdata,
    input                         pready,
    output                        cmd_rdy,
    output                        psel,
    output                        penable,
    output                        pwrite,
    output [ADDR_WD - 1 : 0]      paddr,
    output [DATA_WD - 1 : 0]      pwdata,
    output                        read_vld,
    output [DATA_WD - 1 : 0]      read_data
);

//----------------------------tx----------------------------------------------

localparam [1:0] IDLE = 2'b00;
localparam [1:0] SETUP = 2'b01;
localparam [1:0] ACCESS = 2'b11;

reg [1:0] state,next_state;

reg r_psel,r_penable;
assign psel = r_psel;
assign penable = r_penable;

reg [DATA_WD + ADDR_WD : 0] r_cmd_in;

//control path
wire cmd_fire;
assign cmd_fire = cmd_vld && cmd_rdy;
assign cmd_rdy = state == IDLE;

always @(posedge clk or negedge rst_n) begin
    if(!rst_n) begin
        state <= IDLE;
    end
    else begin
        state <= next_state;
    end
end

always @(*) begin
    case(state)
        IDLE: begin
            if(cmd_fire) begin
                next_state = SETUP;
            end
            else begin
                next_state = IDLE;
            end
        end
        SETUP: begin
            next_state = ACCESS;
        end
        ACCESS: begin
            if(pready) begin
                next_state = IDLE;
            end
            else begin
                next_state = ACCESS;
            end
        end
        default: begin
            next_state = IDLE;
        end
    endcase
end

always @(*) begin
    r_psel = 'b0;
    r_penable = 'b0;
    case(state)
        IDLE: begin
        end
        SETUP: begin
            r_psel = 1'b1;
        end
        ACCESS: begin
            r_psel = 1'b1;
            r_penable = 1'b1;
        end
        default: begin
        end
    endcase
end


//data path
always @(posedge clk or negedge rst_n) begin
    if(!rst_n) begin
        r_cmd_in <= 'b0;
    end
    else if(cmd_fire) begin
        r_cmd_in <= cmd_in;
    end
end

assign paddr  = r_cmd_in[DATA_WD + ADDR_WD - 1 : DATA_WD];
assign pwdata = r_cmd_in[DATA_WD - 1 : 0];
assign pwrite = r_cmd_in[DATA_WD + ADDR_WD];

//---------------------------------------------rx----------------------------------

assign read_data = prdata;
assign read_vld = ~pwrite && pready;

endmodule

apb_design_spec/code/apb_top.v
module apb_top #(
    parameter DATA_WD = 8,
    parameter ADDR_WD = 8 
) (
    input                         clk,
    input                         rst_n,
    input [DATA_WD + ADDR_WD : 0] cmd_in,
    input                         cmd_vld,
    output                        cmd_rdy,
    output                        read_vld,
    output [DATA_WD - 1 : 0]      read_data
);

    wire psel,penable,pwrite,pready;
    wire [DATA_WD - 1 : 0] pwdata;
    wire [ADDR_WD - 1 : 0] paddr;
    wire [DATA_WD - 1 : 0] prdata;

   apb_master  #(
              .DATA_WD(DATA_WD),
              .ADDR_WD(ADDR_WD)
            )u_apb_master(
              .clk(clk),
              .rst_n(rst_n),
              .cmd_in(cmd_in),
              .cmd_vld(cmd_vld),
              .prdata(prdata),
              .pready(pready),
              .cmd_rdy(cmd_rdy),
              .psel(psel),
              .penable(penable),
              .pwrite(pwrite),
              .paddr(paddr),
              .pwdata(pwdata),
              .read_vld(read_vld),
              .read_data(read_data)
            );

   apb_slave  #(
             .DATA_WD(DATA_WD),
             .ADDR_WD(ADDR_WD)
           )u_apb_slave(
             .clk(clk),
             .rst_n(rst_n),
             .psel(psel),
             .penable(penable),
             .pwrite(pwrite),
             .paddr(paddr),
             .pwdata(pwdata),
             .prdata(prdata),
             .pready(pready)
           );

                          
endmodule

apb_design_spec/code/tb_apb.v
module tb_apb();

localparam DATA_WD = 4;
localparam ADDR_WD = 4;
localparam HALF_CYCLE = 5;

reg                         clk;
reg                         rst_n;
reg [DATA_WD + ADDR_WD : 0] cmd_in;
reg                         cmd_vld;
wire                        cmd_rdy;
wire                        read_vld;
wire [DATA_WD - 1 : 0]      read_data;


apb_top #(
       .DATA_WD(DATA_WD),
       .ADDR_WD(ADDR_WD)
     )u_apb_top (
       .clk(clk),
       .rst_n(rst_n),
       .cmd_in(cmd_in),
       .cmd_vld(cmd_vld),
       .cmd_rdy(cmd_rdy),
       .read_vld(read_vld),
       .read_data(read_data)
     );


reg [ADDR_WD : 0] addr_cnt;

wire cmd_fire;
assign cmd_fire = cmd_vld && cmd_rdy;

wire                   write;
wire [ADDR_WD - 1 : 0] cmd_data;
wire [ADDR_WD - 1 : 0] cmd_addr;

assign write = !addr_cnt[ADDR_WD];
assign cmd_data = addr_cnt[ADDR_WD - 1 : 0];
assign cmd_addr = addr_cnt[ADDR_WD - 1 : 0];

initial begin
    clk = 0;
    forever #HALF_CYCLE clk = ~clk;
end

initial begin
     rst_n = 0;
     #50
     rst_n = 1;
     #1950 $finish();
end

always @(posedge clk or negedge rst_n) begin
    if(!rst_n) begin
        addr_cnt <= 'b0;
    end
    else if(cmd_fire) begin
        addr_cnt <= addr_cnt + 1'b1;
    end
end

always @(posedge clk or negedge rst_n) begin
    if(!rst_n) begin
        cmd_vld <= 'b0;
        cmd_in <= 'b0;
    end
    else begin
        cmd_vld <= 1'b1;
        cmd_in <= {write,cmd_addr,cmd_data};
    end
end

initial begin
    $dumpfile("test.vcd");
    $dumpvars;
end

endmodule

apb_design_spec/sim/test.vcd
$date
	Sun Apr 16 19:36:13 2023
$end
$version
	Icarus Verilog
$end
$timescale
	1s
$end
$scope module tb_apb $end
$var wire 1 ! cmd_fire $end
$var wire 1 " write $end
$var wire 1 # read_vld $end
$var wire 4 $ read_data [3:0] $end
$var wire 1 % cmd_rdy $end
$var wire 4 & cmd_data [3:0] $end
$var wire 4 ' cmd_addr [3:0] $end
$var reg 5 ( addr_cnt [4:0] $end
$var reg 1 ) clk $end
$var reg 9 * cmd_in [8:0] $end
$var reg 1 + cmd_vld $end
$var reg 1 , rst_n $end
$scope module u_apb_top $end
$var wire 1 ) clk $end
$var wire 9 - cmd_in [8:0] $end
$var wire 1 + cmd_vld $end
$var wire 1 , rst_n $end
$var wire 1 # read_vld $end
$var wire 4 . read_data [3:0] $end
$var wire 1 / pwrite $end
$var wire 4 0 pwdata [3:0] $end
$var wire 1 1 psel $end
$var wire 1 2 pready $end
$var wire 4 3 prdata [3:0] $end
$var wire 1 4 penable $end
$var wire 4 5 paddr [3:0] $end
$var wire 1 % cmd_rdy $end
$scope module u_apb_master $end
$var wire 1 ) clk $end
$var wire 1 6 cmd_fire $end
$var wire 9 7 cmd_in [8:0] $end
$var wire 1 + cmd_vld $end
$var wire 4 8 read_data [3:0] $end
$var wire 1 # read_vld $end
$var wire 1 , rst_n $end
$var wire 1 / pwrite $end
$var wire 4 9 pwdata [3:0] $end
$var wire 1 1 psel $end
$var wire 1 2 pready $end
$var wire 4 : prdata [3:0] $end
$var wire 1 4 penable $end
$var wire 4 ; paddr [3:0] $end
$var wire 1 % cmd_rdy $end
$var reg 2 < next_state [1:0] $end
$var reg 9 = r_cmd_in [8:0] $end
$var reg 1 4 r_penable $end
$var reg 1 1 r_psel $end
$var reg 2 > state [1:0] $end
$upscope $end
$scope module u_apb_slave $end
$var wire 1 ? apb_fire $end
$var wire 1 ) clk $end
$var wire 4 @ paddr [3:0] $end
$var wire 1 4 penable $end
$var wire 4 A prdata [3:0] $end
$var wire 1 1 psel $end
$var wire 4 B pwdata [3:0] $end
$var wire 1 / pwrite $end
$var wire 1 , rst_n $end
$var wire 1 2 pready $end
$var reg 2 C next_state [1:0] $end
$var reg 1 2 r_pready $end
$var reg 2 D state [1:0] $end
$upscope $end
$upscope $end
$upscope $end
$enddefinitions $end
#0
$dumpvars
b0 D
b0 C
b0 B
bx A
b0 @
0?
b0 >
b0 =
b0 <
b0 ;
bx :
b0 9
bx 8
bx 7
x6
b0 5
04
bx 3
02
01
b0 0
0/
bx .
bx -
0,
x+
bx *
0)
bx (
bx '
bx &
1%
bx $
0#
x"
x!
$end
#5
1"
b0 &
b0 '
06
0!
b0 (
b0 *
b0 -
b0 7
0+
1)
#10
0)
#15
1)
#20
0)
#25
1)
#30
0)
#35
1)
#40
0)
#45
1)
#50
0)
1,
#55
b1 <
16
1!
b100000000 *
b100000000 -
b100000000 7
1+
1)
#60
0)
#65
b1 C
b1 &
b1 '
1/
11
b11 <
06
0!
b1 (
b100000000 =
0%
b1 >
1)
#70
0)
#75
14
11
b11 C
b11 >
b1 D
b100010001 *
b100010001 -
b100010001 7
1)
#80
0)
#85
1?
b0 <
b1 C
12
b11 D
1)
#90
0)
#95
0?
04
01
b1 <
16
1!
02
b11 C
1%
b0 >
b1 D
b0 $
b0 .
b0 8
b0 3
b0 :
b0 A
1)
#100
0)
#105
b10 &
b10 '
bx $
bx .
bx 8
bx 3
bx :
bx A
b1 5
b1 ;
b1 @
b1 0
b1 9
b1 B
11
b11 <
06
0!
b10 (
b11 D
b100010001 =
0%
b1 >
1)
#110
0)
#115
1?
b0 <
b1 C
12
14
11
b11 >
b100100010 *
b100100010 -
b100100010 7
1)
#120
0)
#125
0?
02
b11 C
04
01
b1 <
16
1!
b1 $
b1 .
b1 8
b1 3
b1 :
b1 A
b1 D
1%
b0 >
1)
#130
0)
#135
11
b11 <
06
0!
bx $
bx .
bx 8
bx 3
bx :
bx A
b10 5
b10 ;
b10 @
b10 0
b10 9
b10 B
b11 &
b11 '
0%
b1 >
b100100010 =
b11 D
b11 (
1)
#140
0)
#145
1?
b0 <
b1 C
12
14
11
b100110011 *
b100110011 -
b100110011 7
b11 >
1)
#150
0)
#155
0?
04
01
b1 <
16
1!
02
b11 C
1%
b0 >
b1 D
b10 $
b10 .
b10 8
b10 3
b10 :
b10 A
1)
#160
0)
#165
b100 &
b100 '
bx $
bx .
bx 8
bx 3
bx :
bx A
b11 5
b11 ;
b11 @
b11 0
b11 9
b11 B
11
b11 <
06
0!
b100 (
b11 D
b100110011 =
0%
b1 >
1)
#170
0)
#175
1?
b0 <
b1 C
12
14
11
b11 >
b101000100 *
b101000100 -
b101000100 7
1)
#180
0)
#185
0?
02
b11 C
04
01
b1 <
16
1!
b11 $
b11 .
b11 8
b11 3
b11 :
b11 A
b1 D
1%
b0 >
1)
#190
0)
#195
11
b11 <
06
0!
bx $
bx .
bx 8
bx 3
bx :
bx A
b100 5
b100 ;
b100 @
b100 0
b100 9
b100 B
b101 &
b101 '
0%
b1 >
b101000100 =
b11 D
b101 (
1)
#200
0)
#205
1?
b0 <
b1 C
12
14
11
b101010101 *
b101010101 -
b101010101 7
b11 >
1)
#210
0)
#215
0?
04
01
b1 <
16
1!
02
b11 C
1%
b0 >
b1 D
b100 $
b100 .
b100 8
b100 3
b100 :
b100 A
1)
#220
0)
#225
b110 &
b110 '
bx $
bx .
bx 8
bx 3
bx :
bx A
b101 5
b101 ;
b101 @
b101 0
b101 9
b101 B
11
b11 <
06
0!
b110 (
b11 D
b101010101 =
0%
b1 >
1)
#230
0)
#235
1?
b0 <
b1 C
12
14
11
b11 >
b101100110 *
b101100110 -
b101100110 7
1)
#240
0)
#245
0?
02
b11 C
04
01
b1 <
16
1!
b101 $
b101 .
b101 8
b101 3
b101 :
b101 A
b1 D
1%
b0 >
1)
#250
0)
#255
11
b11 <
06
0!
bx $
bx .
bx 8
bx 3
bx :
bx A
b110 5
b110 ;
b110 @
b110 0
b110 9
b110 B
b111 &
b111 '
0%
b1 >
b101100110 =
b11 D
b111 (
1)
#260
0)
#265
1?
b0 <
b1 C
12
14
11
b101110111 *
b101110111 -
b101110111 7
b11 >
1)
#270
0)
#275
0?
04
01
b1 <
16
1!
02
b11 C
1%
b0 >
b1 D
b110 $
b110 .
b110 8
b110 3
b110 :
b110 A
1)
#280
0)
#285
b1000 &
b1000 '
bx $
bx .
bx 8
bx 3
bx :
bx A
b111 5
b111 ;
b111 @
b111 0
b111 9
b111 B
11
b11 <
06
0!
b1000 (
b11 D
b101110111 =
0%
b1 >
1)
#290
0)
#295
1?
b0 <
b1 C
12
14
11
b11 >
b110001000 *
b110001000 -
b110001000 7
1)
#300
0)
#305
0?
02
b11 C
04
01
b1 <
16
1!
b111 $
b111 .
b111 8
b111 3
b111 :
b111 A
b1 D
1%
b0 >
1)
#310
0)
#315
11
b11 <
06
0!
bx $
bx .
bx 8
bx 3
bx :
bx A
b1000 5
b1000 ;
b1000 @
b1000 0
b1000 9
b1000 B
b1001 &
b1001 '
0%
b1 >
b110001000 =
b11 D
b1001 (
1)
#320
0)
#325
1?
b0 <
b1 C
12
14
11
b110011001 *
b110011001 -
b110011001 7
b11 >
1)
#330
0)
#335
0?
04
01
b1 <
16
1!
02
b11 C
1%
b0 >
b1 D
b1000 $
b1000 .
b1000 8
b1000 3
b1000 :
b1000 A
1)
#340
0)
#345
b1010 &
b1010 '
bx $
bx .
bx 8
bx 3
bx :
bx A
b1001 5
b1001 ;
b1001 @
b1001 0
b1001 9
b1001 B
11
b11 <
06
0!
b1010 (
b11 D
b110011001 =
0%
b1 >
1)
#350
0)
#355
1?
b0 <
b1 C
12
14
11
b11 >
b110101010 *
b110101010 -
b110101010 7
1)
#360
0)
#365
0?
02
b11 C
04
01
b1 <
16
1!
b1001 $
b1001 .
b1001 8
b1001 3
b1001 :
b1001 A
b1 D
1%
b0 >
1)
#370
0)
#375
11
b11 <
06
0!
bx $
bx .
bx 8
bx 3
bx :
bx A
b1010 5
b1010 ;
b1010 @
b1010 0
b1010 9
b1010 B
b1011 &
b1011 '
0%
b1 >
b110101010 =
b11 D
b1011 (
1)
#380
0)
#385
1?
b0 <
b1 C
12
14
11
b110111011 *
b110111011 -
b110111011 7
b11 >
1)
#390
0)
#395
0?
04
01
b1 <
16
1!
02
b11 C
1%
b0 >
b1 D
b1010 $
b1010 .
b1010 8
b1010 3
b1010 :
b1010 A
1)
#400
0)
#405
b1100 &
b1100 '
bx $
bx .
bx 8
bx 3
bx :
bx A
b1011 5
b1011 ;
b1011 @
b1011 0
b1011 9
b1011 B
11
b11 <
06
0!
b1100 (
b11 D
b110111011 =
0%
b1 >
1)
#410
0)
#415
1?
b0 <
b1 C
12
14
11
b11 >
b111001100 *
b111001100 -
b111001100 7
1)
#420
0)
#425
0?
02
b11 C
04
01
b1 <
16
1!
b1011 $
b1011 .
b1011 8
b1011 3
b1011 :
b1011 A
b1 D
1%
b0 >
1)
#430
0)
#435
11
b11 <
06
0!
bx $
bx .
bx 8
bx 3
bx :
bx A
b1100 5
b1100 ;
b1100 @
b1100 0
b1100 9
b1100 B
b1101 &
b1101 '
0%
b1 >
b111001100 =
b11 D
b1101 (
1)
#440
0)
#445
1?
b0 <
b1 C
12
14
11
b111011101 *
b111011101 -
b111011101 7
b11 >
1)
#450
0)
#455
0?
04
01
b1 <
16
1!
02
b11 C
1%
b0 >
b1 D
b1100 $
b1100 .
b1100 8
b1100 3
b1100 :
b1100 A
1)
#460
0)
#465
b1110 &
b1110 '
bx $
bx .
bx 8
bx 3
bx :
bx A
b1101 5
b1101 ;
b1101 @
b1101 0
b1101 9
b1101 B
11
b11 <
06
0!
b1110 (
b11 D
b111011101 =
0%
b1 >
1)
#470
0)
#475
1?
b0 <
b1 C
12
14
11
b11 >
b111101110 *
b111101110 -
b111101110 7
1)
#480
0)
#485
0?
02
b11 C
04
01
b1 <
16
1!
b1101 $
b1101 .
b1101 8
b1101 3
b1101 :
b1101 A
b1 D
1%
b0 >
1)
#490
0)
#495
11
b11 <
06
0!
bx $
bx .
bx 8
bx 3
bx :
bx A
b1110 5
b1110 ;
b1110 @
b1110 0
b1110 9
b1110 B
b1111 &
b1111 '
0%
b1 >
b111101110 =
b11 D
b1111 (
1)
#500
0)
#505
1?
b0 <
b1 C
12
14
11
b111111111 *
b111111111 -
b111111111 7
b11 >
1)
#510
0)
#515
0?
04
01
b1 <
16
1!
02
b11 C
1%
b0 >
b1 D
b1110 $
b1110 .
b1110 8
b1110 3
b1110 :
b1110 A
1)
#520
0)
#525
0"
b0 &
b0 '
bx $
bx .
bx 8
bx 3
bx :
bx A
b1111 5
b1111 ;
b1111 @
b1111 0
b1111 9
b1111 B
11
b11 <
06
0!
b10000 (
b11 D
b111111111 =
0%
b1 >
1)
#530
0)
#535
1?
b0 <
b1 C
12
14
11
b11 >
b0 *
b0 -
b0 7
1)
#540
0)
#545
0?
02
b11 C
04
01
b1 <
16
1!
b1111 $
b1111 .
b1111 8
b1111 3
b1111 :
b1111 A
b1 D
1%
b0 >
1)
#550
0)
#555
11
b11 <
06
0!
b0 $
b0 .
b0 8
b0 3
b0 :
b0 A
b0 5
b0 ;
b0 @
b0 0
b0 9
b0 B
0/
b1 &
b1 '
0%
b1 >
b0 =
b11 D
b10001 (
1)
#560
0)
#565
1?
1#
b0 <
b1 C
12
14
11
b10001 *
b10001 -
b10001 7
b11 >
1)
#570
0)
#575
0?
0#
04
01
b1 <
16
1!
02
b11 C
1%
b0 >
b1 D
1)
#580
0)
#585
b10 &
b10 '
b1 $
b1 .
b1 8
b1 3
b1 :
b1 A
b1 5
b1 ;
b1 @
b1 0
b1 9
b1 B
11
b11 <
06
0!
b10010 (
b11 D
b10001 =
0%
b1 >
1)
#590
0)
#595
1?
1#
b0 <
b1 C
12
14
11
b11 >
b100010 *
b100010 -
b100010 7
1)
#600
0)
#605
0?
0#
02
b11 C
04
01
b1 <
16
1!
b1 D
1%
b0 >
1)
#610
0)
#615
11
b11 <
06
0!
b10 $
b10 .
b10 8
b10 3
b10 :
b10 A
b10 5
b10 ;
b10 @
b10 0
b10 9
b10 B
b11 &
b11 '
0%
b1 >
b100010 =
b11 D
b10011 (
1)
#620
0)
#625
1?
1#
b0 <
b1 C
12
14
11
b110011 *
b110011 -
b110011 7
b11 >
1)
#630
0)
#635
0?
0#
04
01
b1 <
16
1!
02
b11 C
1%
b0 >
b1 D
1)
#640
0)
#645
b100 &
b100 '
b11 $
b11 .
b11 8
b11 3
b11 :
b11 A
b11 5
b11 ;
b11 @
b11 0
b11 9
b11 B
11
b11 <
06
0!
b10100 (
b11 D
b110011 =
0%
b1 >
1)
#650
0)
#655
1?
1#
b0 <
b1 C
12
14
11
b11 >
b1000100 *
b1000100 -
b1000100 7
1)
#660
0)
#665
0?
0#
02
b11 C
04
01
b1 <
16
1!
b1 D
1%
b0 >
1)
#670
0)
#675
11
b11 <
06
0!
b100 $
b100 .
b100 8
b100 3
b100 :
b100 A
b100 5
b100 ;
b100 @
b100 0
b100 9
b100 B
b101 &
b101 '
0%
b1 >
b1000100 =
b11 D
b10101 (
1)
#680
0)
#685
1?
1#
b0 <
b1 C
12
14
11
b1010101 *
b1010101 -
b1010101 7
b11 >
1)
#690
0)
#695
0?
0#
04
01
b1 <
16
1!
02
b11 C
1%
b0 >
b1 D
1)
#700
0)
#705
b110 &
b110 '
b101 $
b101 .
b101 8
b101 3
b101 :
b101 A
b101 5
b101 ;
b101 @
b101 0
b101 9
b101 B
11
b11 <
06
0!
b10110 (
b11 D
b1010101 =
0%
b1 >
1)
#710
0)
#715
1?
1#
b0 <
b1 C
12
14
11
b11 >
b1100110 *
b1100110 -
b1100110 7
1)
#720
0)
#725
0?
0#
02
b11 C
04
01
b1 <
16
1!
b1 D
1%
b0 >
1)
#730
0)
#735
11
b11 <
06
0!
b110 $
b110 .
b110 8
b110 3
b110 :
b110 A
b110 5
b110 ;
b110 @
b110 0
b110 9
b110 B
b111 &
b111 '
0%
b1 >
b1100110 =
b11 D
b10111 (
1)
#740
0)
#745
1?
1#
b0 <
b1 C
12
14
11
b1110111 *
b1110111 -
b1110111 7
b11 >
1)
#750
0)
#755
0?
0#
04
01
b1 <
16
1!
02
b11 C
1%
b0 >
b1 D
1)
#760
0)
#765
b1000 &
b1000 '
b111 $
b111 .
b111 8
b111 3
b111 :
b111 A
b111 5
b111 ;
b111 @
b111 0
b111 9
b111 B
11
b11 <
06
0!
b11000 (
b11 D
b1110111 =
0%
b1 >
1)
#770
0)
#775
1?
1#
b0 <
b1 C
12
14
11
b11 >
b10001000 *
b10001000 -
b10001000 7
1)
#780
0)
#785
0?
0#
02
b11 C
04
01
b1 <
16
1!
b1 D
1%
b0 >
1)
#790
0)
#795
11
b11 <
06
0!
b1000 $
b1000 .
b1000 8
b1000 3
b1000 :
b1000 A
b1000 5
b1000 ;
b1000 @
b1000 0
b1000 9
b1000 B
b1001 &
b1001 '
0%
b1 >
b10001000 =
b11 D
b11001 (
1)
#800
0)
#805
1?
1#
b0 <
b1 C
12
14
11
b10011001 *
b10011001 -
b10011001 7
b11 >
1)
#810
0)
#815
0?
0#
04
01
b1 <
16
1!
02
b11 C
1%
b0 >
b1 D
1)
#820
0)
#825
b1010 &
b1010 '
b1001 $
b1001 .
b1001 8
b1001 3
b1001 :
b1001 A
b1001 5
b1001 ;
b1001 @
b1001 0
b1001 9
b1001 B
11
b11 <
06
0!
b11010 (
b11 D
b10011001 =
0%
b1 >
1)
#830
0)
#835
1?
1#
b0 <
b1 C
12
14
11
b11 >
b10101010 *
b10101010 -
b10101010 7
1)
#840
0)
#845
0?
0#
02
b11 C
04
01
b1 <
16
1!
b1 D
1%
b0 >
1)
#850
0)
#855
11
b11 <
06
0!
b1010 $
b1010 .
b1010 8
b1010 3
b1010 :
b1010 A
b1010 5
b1010 ;
b1010 @
b1010 0
b1010 9
b1010 B
b1011 &
b1011 '
0%
b1 >
b10101010 =
b11 D
b11011 (
1)
#860
0)
#865
1?
1#
b0 <
b1 C
12
14
11
b10111011 *
b10111011 -
b10111011 7
b11 >
1)
#870
0)
#875
0?
0#
04
01
b1 <
16
1!
02
b11 C
1%
b0 >
b1 D
1)
#880
0)
#885
b1100 &
b1100 '
b1011 $
b1011 .
b1011 8
b1011 3
b1011 :
b1011 A
b1011 5
b1011 ;
b1011 @
b1011 0
b1011 9
b1011 B
11
b11 <
06
0!
b11100 (
b11 D
b10111011 =
0%
b1 >
1)
#890
0)
#895
1?
1#
b0 <
b1 C
12
14
11
b11 >
b11001100 *
b11001100 -
b11001100 7
1)
#900
0)
#905
0?
0#
02
b11 C
04
01
b1 <
16
1!
b1 D
1%
b0 >
1)
#910
0)
#915
11
b11 <
06
0!
b1100 $
b1100 .
b1100 8
b1100 3
b1100 :
b1100 A
b1100 5
b1100 ;
b1100 @
b1100 0
b1100 9
b1100 B
b1101 &
b1101 '
0%
b1 >
b11001100 =
b11 D
b11101 (
1)
#920
0)
#925
1?
1#
b0 <
b1 C
12
14
11
b11011101 *
b11011101 -
b11011101 7
b11 >
1)
#930
0)
#935
0?
0#
04
01
b1 <
16
1!
02
b11 C
1%
b0 >
b1 D
1)
#940
0)
#945
b1110 &
b1110 '
b1101 $
b1101 .
b1101 8
b1101 3
b1101 :
b1101 A
b1101 5
b1101 ;
b1101 @
b1101 0
b1101 9
b1101 B
11
b11 <
06
0!
b11110 (
b11 D
b11011101 =
0%
b1 >
1)
#950
0)
#955
1?
1#
b0 <
b1 C
12
14
11
b11 >
b11101110 *
b11101110 -
b11101110 7
1)
#960
0)
#965
0?
0#
02
b11 C
04
01
b1 <
16
1!
b1 D
1%
b0 >
1)
#970
0)
#975
11
b11 <
06
0!
b1110 $
b1110 .
b1110 8
b1110 3
b1110 :
b1110 A
b1110 5
b1110 ;
b1110 @
b1110 0
b1110 9
b1110 B
b1111 &
b1111 '
0%
b1 >
b11101110 =
b11 D
b11111 (
1)
#980
0)
#985
1?
1#
b0 <
b1 C
12
14
11
b11111111 *
b11111111 -
b11111111 7
b11 >
1)
#990
0)
#995
0?
0#
04
01
b1 <
16
1!
02
b11 C
1%
b0 >
b1 D
1)
#1000
0)
#1005
1"
b0 &
b0 '
b1111 $
b1111 .
b1111 8
b1111 3
b1111 :
b1111 A
b1111 5
b1111 ;
b1111 @
b1111 0
b1111 9
b1111 B
11
b11 <
06
0!
b0 (
b11 D
b11111111 =
0%
b1 >
1)
#1010
0)
#1015
1?
1#
b0 <
b1 C
12
14
11
b11 >
b100000000 *
b100000000 -
b100000000 7
1)
#1020
0)
#1025
0?
0#
02
b11 C
04
01
b1 <
16
1!
b1 D
1%
b0 >
1)
#1030
0)
#1035
11
b11 <
06
0!
b0 $
b0 .
b0 8
b0 3
b0 :
b0 A
b0 5
b0 ;
b0 @
b0 0
b0 9
b0 B
1/
b1 &
b1 '
0%
b1 >
b100000000 =
b11 D
b1 (
1)
#1040
0)
#1045
1?
b0 <
b1 C
12
14
11
b100010001 *
b100010001 -
b100010001 7
b11 >
1)
#1050
0)
#1055
0?
04
01
b1 <
16
1!
02
b11 C
1%
b0 >
b1 D
1)
#1060
0)
#1065
b10 &
b10 '
b1 $
b1 .
b1 8
b1 3
b1 :
b1 A
b1 5
b1 ;
b1 @
b1 0
b1 9
b1 B
11
b11 <
06
0!
b10 (
b11 D
b100010001 =
0%
b1 >
1)
#1070
0)
#1075
1?
b0 <
b1 C
12
14
11
b11 >
b100100010 *
b100100010 -
b100100010 7
1)
#1080
0)
#1085
0?
02
b11 C
04
01
b1 <
16
1!
b1 D
1%
b0 >
1)
#1090
0)
#1095
11
b11 <
06
0!
b10 $
b10 .
b10 8
b10 3
b10 :
b10 A
b10 5
b10 ;
b10 @
b10 0
b10 9
b10 B
b11 &
b11 '
0%
b1 >
b100100010 =
b11 D
b11 (
1)
#1100
0)
#1105
1?
b0 <
b1 C
12
14
11
b100110011 *
b100110011 -
b100110011 7
b11 >
1)
#1110
0)
#1115
0?
04
01
b1 <
16
1!
02
b11 C
1%
b0 >
b1 D
1)
#1120
0)
#1125
b100 &
b100 '
b11 $
b11 .
b11 8
b11 3
b11 :
b11 A
b11 5
b11 ;
b11 @
b11 0
b11 9
b11 B
11
b11 <
06
0!
b100 (
b11 D
b100110011 =
0%
b1 >
1)
#1130
0)
#1135
1?
b0 <
b1 C
12
14
11
b11 >
b101000100 *
b101000100 -
b101000100 7
1)
#1140
0)
#1145
0?
02
b11 C
04
01
b1 <
16
1!
b1 D
1%
b0 >
1)
#1150
0)
#1155
11
b11 <
06
0!
b100 $
b100 .
b100 8
b100 3
b100 :
b100 A
b100 5
b100 ;
b100 @
b100 0
b100 9
b100 B
b101 &
b101 '
0%
b1 >
b101000100 =
b11 D
b101 (
1)
#1160
0)
#1165
1?
b0 <
b1 C
12
14
11
b101010101 *
b101010101 -
b101010101 7
b11 >
1)
#1170
0)
#1175
0?
04
01
b1 <
16
1!
02
b11 C
1%
b0 >
b1 D
1)
#1180
0)
#1185
b110 &
b110 '
b101 $
b101 .
b101 8
b101 3
b101 :
b101 A
b101 5
b101 ;
b101 @
b101 0
b101 9
b101 B
11
b11 <
06
0!
b110 (
b11 D
b101010101 =
0%
b1 >
1)
#1190
0)
#1195
1?
b0 <
b1 C
12
14
11
b11 >
b101100110 *
b101100110 -
b101100110 7
1)
#1200
0)
#1205
0?
02
b11 C
04
01
b1 <
16
1!
b1 D
1%
b0 >
1)
#1210
0)
#1215
11
b11 <
06
0!
b110 $
b110 .
b110 8
b110 3
b110 :
b110 A
b110 5
b110 ;
b110 @
b110 0
b110 9
b110 B
b111 &
b111 '
0%
b1 >
b101100110 =
b11 D
b111 (
1)
#1220
0)
#1225
1?
b0 <
b1 C
12
14
11
b101110111 *
b101110111 -
b101110111 7
b11 >
1)
#1230
0)
#1235
0?
04
01
b1 <
16
1!
02
b11 C
1%
b0 >
b1 D
1)
#1240
0)
#1245
b1000 &
b1000 '
b111 $
b111 .
b111 8
b111 3
b111 :
b111 A
b111 5
b111 ;
b111 @
b111 0
b111 9
b111 B
11
b11 <
06
0!
b1000 (
b11 D
b101110111 =
0%
b1 >
1)
#1250
0)
#1255
1?
b0 <
b1 C
12
14
11
b11 >
b110001000 *
b110001000 -
b110001000 7
1)
#1260
0)
#1265
0?
02
b11 C
04
01
b1 <
16
1!
b1 D
1%
b0 >
1)
#1270
0)
#1275
11
b11 <
06
0!
b1000 $
b1000 .
b1000 8
b1000 3
b1000 :
b1000 A
b1000 5
b1000 ;
b1000 @
b1000 0
b1000 9
b1000 B
b1001 &
b1001 '
0%
b1 >
b110001000 =
b11 D
b1001 (
1)
#1280
0)
#1285
1?
b0 <
b1 C
12
14
11
b110011001 *
b110011001 -
b110011001 7
b11 >
1)
#1290
0)
